cv_stream_recorder/__init__.py
cv_stream_recorder/config.py
cv_stream_recorder/helpers.py
cv_stream_recorder/recorder.py
cv_stream_recorder/utils/logging_config.py
cv_stream_recorder-0.1.3.dist-info/licenses/LICENSE
cv_stream_recorder-0.1.3.dist-info/METADATA
cv_stream_recorder-0.1.3.dist-info/WHEEL
cv_stream_recorder-0.1.3.dist-info/top_level.txt
cv_stream_recorder-0.1.3.dist-info/RECORD
