Metadata-Version: 2.4
Name: cv-stream-recorder
Version: 0.1.3
Summary: Record video stream and save it to consecutive chunks
Author-email: DX FutureTech VN <hung.ly@dxfuturetech.com.vn>
License: MIT License
Project-URL: Homepage, https://gitlab.aurora-tech.com/automation/cv-stream-recorder
Project-URL: Bug Tracker, https://gitlab.aurora-tech.com/automation/cv-stream-recorder/-/issues
Keywords: video,stream,recorder
Classifier: Programming Language :: Python :: 3
Classifier: License :: OSI Approved :: MIT License
Classifier: Operating System :: OS Independent
Requires-Python: >=3.11
License-File: LICENSE
Requires-Dist: ffmpeg-python>=0.2.0
Requires-Dist: pydantic-settings>=2.12.0
Dynamic: license-file
